plinear/__init__.py
plinear/bctnn/__init__.py
plinear/bctnn/conv.py
plinear/bctnn/linear.py
plinear/blocks/__init__.py
plinear/blocks/bctnnAttention.py
plinear/blocks/btnnAttention.py
plinear/btnn/RMSNorm.py
plinear/btnn/__init__.py
plinear/btnn/conv.py
plinear/btnn/conv1d.py
plinear/btnn/linear.py
plinear/core/RMSNorm.py
plinear/core/__init__.py
plinear/core/posNet.py
plinear/models/CAS_ViT.py
plinear/models/__init__.py
plinear/models/bctViT.py
plinear/models/btViT.py
plinear/models/cnn_example.py
plinear/models/convMixer.py
plinear/models/vit_example.py
plinear-0.2.0.4.dist-info/LICENSE
plinear-0.2.0.4.dist-info/METADATA
plinear-0.2.0.4.dist-info/WHEEL
plinear-0.2.0.4.dist-info/RECORD
