Metadata-Version: 2.1
Name: plinear
Version: 0.2.0.4
Summary: parallel neural network layer for binarization of ternarization - quantized layers from the beginning
Home-page: https://github.com/Snow0821/plinear
License: MIT
Author: Choi Soon Ho
Author-email: sosaror@gmail.com
Requires-Python: >=3.10,<4.0
Classifier: License :: OSI Approved :: MIT License
Classifier: Programming Language :: Python :: 3
Classifier: Programming Language :: Python :: 3.10
Classifier: Programming Language :: Python :: 3.11
Classifier: Programming Language :: Python :: 3.12
Classifier: Programming Language :: Python :: 3.13
Requires-Dist: numpy (>=1.21,<2.0)
Project-URL: Repository, https://github.com/Snow0821/plinear
